chars_betterlogs/__init__.py
chars_betterlogs/betterLogs.py
chars_betterlogs/logs.py
chars_betterlogs/logs_old.py
chars_betterlogs/internal/args.py
chars_betterlogs/internal/bcolors.py
chars_betterlogs/internal/birdy.py
chars_betterlogs/internal/semver.py
chars_betterlogs-4.0.0.dist-info/METADATA
chars_betterlogs-4.0.0.dist-info/WHEEL
chars_betterlogs-4.0.0.dist-info/licenses/LICENSE
chars_betterlogs-4.0.0.dist-info/RECORD
