Metadata-Version: 2.4
Name: chars-betterlogs
Version: 4.0.0
Summary: A project started to fix a problem I was having with the default python logging library
Project-URL: Homepage, https://github.com/CharGoldenYT/betterLogs
Project-URL: Issues, https://github.com/CharGoldenYT/betterLogs/issues
Author: CharGoldenYT
License-Expression: GPL-3.0-or-later
License-File: LICENSE
Classifier: Operating System :: OS Independent
Classifier: Programming Language :: Python :: 3
Requires-Python: >=3.12
